cardvalidator/__init__.py
cardvalidator/validator.py
cardvalidator_lite-0.1.1.dist-info/METADATA
cardvalidator_lite-0.1.1.dist-info/WHEEL
cardvalidator_lite-0.1.1.dist-info/RECORD
