Metadata-Version: 2.4
Name: cardvalidator-lite
Version: 0.1.1
Summary: A Python library for credit card validation using the Luhn algorithm
Project-URL: Homepage, https://github.com/vishvaRam/CardValidator.git
Project-URL: Repository, https://github.com/vishvaRam/CardValidator.git
Project-URL: Issues, https://github.com/vishvaRam/CardValidator/issues
Author-email: Vishva R <murthyvishva@gmail.com>
License: MIT
Keywords: credit card,luhn,payment,rupay,validation
Classifier: Development Status :: 5 - Production/Stable
Classifier: Intended Audience :: Developers
Classifier: License :: OSI Approved :: MIT License
Classifier: Programming Language :: Python :: 3
Classifier: Programming Language :: Python :: 3.8
Classifier: Programming Language :: Python :: 3.9
Classifier: Programming Language :: Python :: 3.10
Classifier: Programming Language :: Python :: 3.11
Classifier: Programming Language :: Python :: 3.12
Classifier: Programming Language :: Python :: 3.13
Requires-Python: >=3.8
